plone.formwidget.contenttree-1.2.0-py2.7-nspkg.pth
plone/formwidget/contenttree/README.rst
plone/formwidget/contenttree/TODO.txt
plone/formwidget/contenttree/__init__.py
plone/formwidget/contenttree/configure.zcml
plone/formwidget/contenttree/demo.py
plone/formwidget/contenttree/demo.zcml
plone/formwidget/contenttree/display_multiple.pt
plone/formwidget/contenttree/display_single.pt
plone/formwidget/contenttree/fragment.pt
plone/formwidget/contenttree/hidden.pt
plone/formwidget/contenttree/input.pt
plone/formwidget/contenttree/input_recurse.pt
plone/formwidget/contenttree/interfaces.py
plone/formwidget/contenttree/navtree.py
plone/formwidget/contenttree/source.py
plone/formwidget/contenttree/testing.py
plone/formwidget/contenttree/testing.zcml
plone/formwidget/contenttree/utils.py
plone/formwidget/contenttree/widget.py
plone/formwidget/contenttree/jquery-contenttree/contenttree.css
plone/formwidget/contenttree/jquery-contenttree/contenttree.js
plone/formwidget/contenttree/profiles/default/cssregistry.xml
plone/formwidget/contenttree/profiles/default/jsregistry.xml
plone/formwidget/contenttree/profiles/default/metadata.xml
plone/formwidget/contenttree/profiles/uninstall/cssregistry.xml
plone/formwidget/contenttree/profiles/uninstall/jsregistry.xml
plone/formwidget/contenttree/tests/__init__.py
plone/formwidget/contenttree/tests/test_doctests.py
plone/formwidget/contenttree/tests/test_setup.py
plone.formwidget.contenttree-1.2.0.dist-info/METADATA
plone.formwidget.contenttree-1.2.0.dist-info/WHEEL
plone.formwidget.contenttree-1.2.0.dist-info/entry_points.txt
plone.formwidget.contenttree-1.2.0.dist-info/namespace_packages.txt
plone.formwidget.contenttree-1.2.0.dist-info/top_level.txt
plone.formwidget.contenttree-1.2.0.dist-info/RECORD
