Metadata-Version: 2.1
Name: plone.formwidget.contenttree
Version: 1.2.0
Summary: AJAX selection widget for Plone
Home-page: https://github.com/plone/plone.formwidget.contenttree
Author: Martin Aspeli
Author-email: optilude@gmail.com
License: GPL
Keywords: Plone selection widget AJAX
Platform: UNKNOWN
Classifier: Development Status :: 5 - Production/Stable
Classifier: Framework :: Plone
Classifier: Framework :: Plone :: 4.3
Classifier: Framework :: Plone :: 5.0
Classifier: Framework :: Plone :: 5.1
Classifier: Framework :: Plone :: 5.2
Classifier: License :: OSI Approved :: GNU General Public License (GPL)
Classifier: Programming Language :: Python
Classifier: Programming Language :: Python :: 2.7
Classifier: Programming Language :: Python :: 3.6
Classifier: Programming Language :: Python :: 3.7
Classifier: Topic :: Software Development :: Libraries :: Python Modules
Requires-Dist: setuptools
Requires-Dist: z3c.formwidget.query
Requires-Dist: plone.formwidget.autocomplete (>=1.2.0)
Requires-Dist: plone.z3cform (>=0.7.4)
Provides-Extra: test
Requires-Dist: plone.app.testing ; extra == 'test'
Requires-Dist: unittest2 ; extra == 'test'
